cerver/__init__.py
cerver/exceptions.py
cerver/sandbox.py
cerver-0.1.0.dist-info/METADATA
cerver-0.1.0.dist-info/WHEEL
cerver-0.1.0.dist-info/top_level.txt
cerver-0.1.0.dist-info/RECORD
