Metadata-Version: 2.4
Name: cerver
Version: 0.1.0
Summary: Python SDK for Cerver - Sandboxed code execution for AI agents
Author-email: Cerver <hello@cerver.ai>
License: MIT
Project-URL: Homepage, https://cerver.ai
Project-URL: Documentation, https://cerver.ai/docs.html
Project-URL: Repository, https://github.com/gneyal/cerver-python
Keywords: ai,sandbox,code-execution,agents,llm
Classifier: Development Status :: 3 - Alpha
Classifier: Intended Audience :: Developers
Classifier: License :: OSI Approved :: MIT License
Classifier: Programming Language :: Python :: 3
Classifier: Programming Language :: Python :: 3.8
Classifier: Programming Language :: Python :: 3.9
Classifier: Programming Language :: Python :: 3.10
Classifier: Programming Language :: Python :: 3.11
Classifier: Programming Language :: Python :: 3.12
Requires-Python: >=3.8
Requires-Dist: requests>=2.25.0
Provides-Extra: dev
Requires-Dist: pytest>=7.0.0; extra == "dev"
Requires-Dist: pytest-asyncio>=0.21.0; extra == "dev"
